COPYING
ChangeLog
MANIFEST.in
README.md
setup.py
netfilter/__init__.py
netfilter/firewall.py
netfilter/parser.py
netfilter/rule.py
netfilter/table.py
netfilter.egg-info/PKG-INFO
netfilter.egg-info/SOURCES.txt
netfilter.egg-info/dependency_links.txt
netfilter.egg-info/top_level.txt
tests/__init__.py
tests/test_netfilter.py