Metadata-Version: 1.1
Name: netfilter
Version: 0.6.2
Summary: Python modules for manipulating netfilter rules
Home-page: https://github.com/jlaine/python-netfilter
Author: Jeremy Laine
Author-email: jeremy.laine@m4x.org
License: GPLv3+
Platform: UNKNOWN
Classifier: Development Status :: 5 - Production/Stable
Classifier: Intended Audience :: Developers
Classifier: Intended Audience :: System Administrators
Classifier: License :: OSI Approved :: GNU General Public License v3 or later (GPLv3+)
Classifier: Operating System :: POSIX :: Linux
Classifier: Programming Language :: Python
Classifier: Programming Language :: Python :: 2
Classifier: Programming Language :: Python :: 3
Classifier: Topic :: Software Development :: Libraries
Classifier: Topic :: System :: Networking :: Firewalls
Classifier: Topic :: System :: Systems Administration
